{
  "0": {
    "1": {
      "app_num_tx": 0,
      "app_num_replied": 0,
      "app_num_endpoint_rx": 0,
      "app_num_lost": 0,
      "app_reliability": 100,
      "app_num_queue_drops": 0,
      "app_num_tx_limit_drops": 0,
      "app_num_routing_drops": 0,
      "app_num_scheduling_drops": 0,
      "app_num_other_drops": 0,
      "tsch_eb_tx": 35,
      "tsch_eb_rx": 95,
      "tsch_keepalive_tx": 0,
      "tsch_keepalive_rx": 27,
      "mac_tx": 35,
      "mac_tx_unicast": 0,
      "mac_acked": 0,
      "mac_rx": 122,
      "mac_rx_error": 0,
      "mac_rx_collision": 6,
      "mac_ack_error": 0,
      "mac_parent_tx_unicast": 0,
      "mac_parent_acked": 0,
      "mac_parent_rx": 0,
      "slots_rx_idle": 15938,
      "slots_rx_scanning": 0,
      "slots_rx_packet": 0,
      "slots_rx_packet_tx_ack": 27,
      "slots_tx_packet": 35,
      "slots_tx_packet_rx_ack": 0,
      "tsch_join_time_sec": 0,
      "tsch_num_parent_changes": 0,
      "app_latency_min_s": null,
      "app_latency_avg_s": null,
      "app_latency_max_s": null,
      "app_latencies": [],
      "radio_duty_cycle": 5.89,
      "radio_duty_cycle_joined": 5.89,
      "charge_uc": 347715.8,
      "charge_joined_uc": 347715.8,
      "avg_current_uA": 579.5,
      "avg_current_joined_uA": 579.5,
      "routing_tx": 0,
      "routing_rx": 0,
      "routing_join_time_sec": 0,
      "routing_num_parent_changes": 1
    },
    "2": {
      "app_num_tx": 0,
      "app_num_replied": 0,
      "app_num_endpoint_rx": 0,
      "app_num_lost": 0,
      "app_reliability": 100,
      "app_num_queue_drops": 0,
      "app_num_tx_limit_drops": 0,
      "app_num_routing_drops": 0,
      "app_num_scheduling_drops": 0,
      "app_num_other_drops": 0,
      "tsch_eb_tx": 38,
      "tsch_eb_rx": 90,
      "tsch_keepalive_tx": 9,
      "tsch_keepalive_rx": 17,
      "mac_tx": 47,
      "mac_tx_unicast": 9,
      "mac_acked": 9,
      "mac_rx": 107,
      "mac_rx_error": 0,
      "mac_rx_collision": 0,
      "mac_ack_error": 0,
      "mac_parent_tx_unicast": 9,
      "mac_parent_acked": 9,
      "mac_parent_rx": 29,
      "slots_rx_idle": 14864,
      "slots_rx_scanning": 4020,
      "slots_rx_packet": 0,
      "slots_rx_packet_tx_ack": 17,
      "slots_tx_packet": 38,
      "slots_tx_packet_rx_ack": 9,
      "tsch_join_time_sec": 40.2,
      "tsch_num_parent_changes": 1,
      "app_latency_min_s": null,
      "app_latency_avg_s": null,
      "app_latency_max_s": null,
      "app_latencies": [],
      "radio_duty_cycle": 12.196,
      "radio_duty_cycle_joined": 5.496,
      "charge_uc": 605684.5,
      "charge_joined_uc": 324284.5,
      "avg_current_uA": 1009.5,
      "avg_current_joined_uA": 540.5,
      "routing_tx": 0,
      "routing_rx": 0,
      "routing_join_time_sec": 0,
      "routing_num_parent_changes": 1
    },
    "3": {
      "app_num_tx": 0,
      "app_num_replied": 0,
      "app_num_endpoint_rx": 0,
      "app_num_lost": 0,
      "app_reliability": 100,
      "app_num_queue_drops": 0,
      "app_num_tx_limit_drops": 0,
      "app_num_routing_drops": 0,
      "app_num_scheduling_drops": 0,
      "app_num_other_drops": 0,
      "tsch_eb_tx": 39,
      "tsch_eb_rx": 63,
      "tsch_keepalive_tx": 10,
      "tsch_keepalive_rx": 10,
      "mac_tx": 49,
      "mac_tx_unicast": 10,
      "mac_acked": 10,
      "mac_rx": 73,
      "mac_rx_error": 0,
      "mac_rx_collision": 4,
      "mac_ack_error": 0,
      "mac_parent_tx_unicast": 10,
      "mac_parent_acked": 10,
      "mac_parent_rx": 30,
      "slots_rx_idle": 11938,
      "slots_rx_scanning": 15,
      "slots_rx_packet": 0,
      "slots_rx_packet_tx_ack": 10,
      "slots_tx_packet": 39,
      "slots_tx_packet_rx_ack": 10,
      "tsch_join_time_sec": 0.15,
      "tsch_num_parent_changes": 1,
      "app_latency_min_s": null,
      "app_latency_avg_s": null,
      "app_latency_max_s": null,
      "app_latencies": [],
      "radio_duty_cycle": 4.446,
      "radio_duty_cycle_joined": 4.421,
      "charge_uc": 261498.7,
      "charge_joined_uc": 260448.7,
      "avg_current_uA": 435.8,
      "avg_current_joined_uA": 434.1,
      "routing_tx": 0,
      "routing_rx": 0,
      "routing_join_time_sec": 0,
      "routing_num_parent_changes": 1
    },
    "4": {
      "app_num_tx": 0,
      "app_num_replied": 0,
      "app_num_endpoint_rx": 0,
      "app_num_lost": 0,
      "app_reliability": 100,
      "app_num_queue_drops": 0,
      "app_num_tx_limit_drops": 0,
      "app_num_routing_drops": 0,
      "app_num_scheduling_drops": 0,
      "app_num_other_drops": 0,
      "tsch_eb_tx": 29,
      "tsch_eb_rx": 27,
      "tsch_keepalive_tx": 8,
      "tsch_keepalive_rx": 0,
      "mac_tx": 37,
      "mac_tx_unicast": 8,
      "mac_acked": 8,
      "mac_rx": 27,
      "mac_rx_error": 0,
      "mac_rx_collision": 0,
      "mac_ack_error": 0,
      "mac_parent_tx_unicast": 8,
      "mac_parent_acked": 8,
      "mac_parent_rx": 26,
      "slots_rx_idle": 6689,
      "slots_rx_scanning": 9555,
      "slots_rx_packet": 0,
      "slots_rx_packet_tx_ack": 0,
      "slots_tx_packet": 29,
      "slots_tx_packet_rx_ack": 8,
      "tsch_join_time_sec": 95.55,
      "tsch_num_parent_changes": 1,
      "app_latency_min_s": null,
      "app_latency_avg_s": null,
      "app_latency_max_s": null,
      "app_latencies": [],
      "radio_duty_cycle": 18.415,
      "radio_duty_cycle_joined": 2.49,
      "charge_uc": 814782.4,
      "charge_joined_uc": 145932.4,
      "avg_current_uA": 1358,
      "avg_current_joined_uA": 243.2,
      "routing_tx": 0,
      "routing_rx": 0,
      "routing_join_time_sec": 0,
      "routing_num_parent_changes": 1
    },
    "5": {
      "app_num_tx": 0,
      "app_num_replied": 0,
      "app_num_endpoint_rx": 0,
      "app_num_lost": 0,
      "app_reliability": 100,
      "app_num_queue_drops": 0,
      "app_num_tx_limit_drops": 0,
      "app_num_routing_drops": 0,
      "app_num_scheduling_drops": 0,
      "app_num_other_drops": 0,
      "tsch_eb_tx": 37,
      "tsch_eb_rx": 37,
      "tsch_keepalive_tx": 9,
      "tsch_keepalive_rx": 0,
      "mac_tx": 46,
      "mac_tx_unicast": 9,
      "mac_acked": 9,
      "mac_rx": 37,
      "mac_rx_error": 0,
      "mac_rx_collision": 0,
      "mac_ack_error": 0,
      "mac_parent_tx_unicast": 9,
      "mac_parent_acked": 9,
      "mac_parent_rx": 36,
      "slots_rx_idle": 7412,
      "slots_rx_scanning": 4065,
      "slots_rx_packet": 0,
      "slots_rx_packet_tx_ack": 0,
      "slots_tx_packet": 37,
      "slots_tx_packet_rx_ack": 9,
      "tsch_join_time_sec": 40.65,
      "tsch_num_parent_changes": 1,
      "app_latency_min_s": null,
      "app_latency_avg_s": null,
      "app_latency_max_s": null,
      "app_latencies": [],
      "radio_duty_cycle": 9.532,
      "radio_duty_cycle_joined": 2.757,
      "charge_uc": 446255.9,
      "charge_joined_uc": 161705.9,
      "avg_current_uA": 743.8,
      "avg_current_joined_uA": 269.5,
      "routing_tx": 0,
      "routing_rx": 0,
      "routing_join_time_sec": 0,
      "routing_num_parent_changes": 1
    },
    "6": {
      "app_num_tx": 0,
      "app_num_replied": 0,
      "app_num_endpoint_rx": 0,
      "app_num_lost": 0,
      "app_reliability": 100,
      "app_num_queue_drops": 0,
      "app_num_tx_limit_drops": 0,
      "app_num_routing_drops": 0,
      "app_num_scheduling_drops": 0,
      "app_num_other_drops": 0,
      "tsch_eb_tx": 26,
      "tsch_eb_rx": 43,
      "tsch_keepalive_tx": 8,
      "tsch_keepalive_rx": 2,
      "mac_tx": 34,
      "mac_tx_unicast": 8,
      "mac_acked": 8,
      "mac_rx": 173,
      "mac_rx_error": 0,
      "mac_rx_collision": 0,
      "mac_ack_error": 0,
      "mac_parent_tx_unicast": 8,
      "mac_parent_acked": 8,
      "mac_parent_rx": 28,
      "slots_rx_idle": 9082,
      "slots_rx_scanning": 13770,
      "slots_rx_packet": 0,
      "slots_rx_packet_tx_ack": 130,
      "slots_tx_packet": 26,
      "slots_tx_packet_rx_ack": 8,
      "tsch_join_time_sec": 137.7,
      "tsch_num_parent_changes": 1,
      "app_latency_min_s": null,
      "app_latency_avg_s": null,
      "app_latency_max_s": null,
      "app_latencies": [],
      "radio_duty_cycle": 26.422,
      "radio_duty_cycle_joined": 3.472,
      "charge_uc": 1162039.9,
      "charge_joined_uc": 198139.9,
      "avg_current_uA": 1936.7,
      "avg_current_joined_uA": 330.2,
      "routing_tx": 0,
      "routing_rx": 0,
      "routing_join_time_sec": 0,
      "routing_num_parent_changes": 1
    },
    "7": {
      "app_num_tx": 0,
      "app_num_replied": 0,
      "app_num_endpoint_rx": 0,
      "app_num_lost": 0,
      "app_reliability": 100,
      "app_num_queue_drops": 0,
      "app_num_tx_limit_drops": 0,
      "app_num_routing_drops": 0,
      "app_num_scheduling_drops": 0,
      "app_num_other_drops": 0,
      "tsch_eb_tx": 35,
      "tsch_eb_rx": 63,
      "tsch_keepalive_tx": 10,
      "tsch_keepalive_rx": 8,
      "mac_tx": 45,
      "mac_tx_unicast": 10,
      "mac_acked": 10,
      "mac_rx": 71,
      "mac_rx_error": 0,
      "mac_rx_collision": 4,
      "mac_ack_error": 0,
      "mac_parent_tx_unicast": 10,
      "mac_parent_acked": 10,
      "mac_parent_rx": 34,
      "slots_rx_idle": 11485,
      "slots_rx_scanning": 2310,
      "slots_rx_packet": 0,
      "slots_rx_packet_tx_ack": 8,
      "slots_tx_packet": 35,
      "slots_tx_packet_rx_ack": 10,
      "tsch_join_time_sec": 23.1,
      "tsch_num_parent_changes": 1,
      "app_latency_min_s": null,
      "app_latency_avg_s": null,
      "app_latency_max_s": null,
      "app_latencies": [],
      "radio_duty_cycle": 8.104,
      "radio_duty_cycle_joined": 4.254,
      "charge_uc": 412265.7,
      "charge_joined_uc": 250565.7,
      "avg_current_uA": 687.1,
      "avg_current_joined_uA": 417.6,
      "routing_tx": 0,
      "routing_rx": 0,
      "routing_join_time_sec": 0,
      "routing_num_parent_changes": 1
    },
    "8": {
      "app_num_tx": 0,
      "app_num_replied": 0,
      "app_num_endpoint_rx": 0,
      "app_num_lost": 0,
      "app_reliability": 100,
      "app_num_queue_drops": 0,
      "app_num_tx_limit_drops": 0,
      "app_num_routing_drops": 0,
      "app_num_scheduling_drops": 0,
      "app_num_other_drops": 0,
      "tsch_eb_tx": 14,
      "tsch_eb_rx": 39,
      "tsch_keepalive_tx": 2,
      "tsch_keepalive_rx": 5,
      "mac_tx": 144,
      "mac_tx_unicast": 130,
      "mac_acked": 130,
      "mac_rx": 172,
      "mac_rx_error": 0,
      "mac_rx_collision": 4,
      "mac_ack_error": 0,
      "mac_parent_tx_unicast": 130,
      "mac_parent_acked": 130,
      "mac_parent_rx": 15,
      "slots_rx_idle": 8663,
      "slots_rx_scanning": 26475,
      "slots_rx_packet": 0,
      "slots_rx_packet_tx_ack": 133,
      "slots_tx_packet": 14,
      "slots_tx_packet_rx_ack": 130,
      "tsch_join_time_sec": 264.75,
      "tsch_num_parent_changes": 1,
      "app_latency_min_s": null,
      "app_latency_avg_s": null,
      "app_latency_max_s": null,
      "app_latencies": [],
      "radio_duty_cycle": 47.544,
      "radio_duty_cycle_joined": 3.419,
      "charge_uc": 2042248.7,
      "charge_joined_uc": 188998.7,
      "avg_current_uA": 3403.7,
      "avg_current_joined_uA": 315,
      "routing_tx": 0,
      "routing_rx": 0,
      "routing_join_time_sec": 0,
      "routing_num_parent_changes": 1
    },
    "9": {
      "app_num_tx": 0,
      "app_num_replied": 0,
      "app_num_endpoint_rx": 0,
      "app_num_lost": 0,
      "app_reliability": 100,
      "app_num_queue_drops": 0,
      "app_num_tx_limit_drops": 0,
      "app_num_routing_drops": 0,
      "app_num_scheduling_drops": 0,
      "app_num_other_drops": 0,
      "tsch_eb_tx": 14,
      "tsch_eb_rx": 13,
      "tsch_keepalive_tx": 5,
      "tsch_keepalive_rx": 0,
      "mac_tx": 19,
      "mac_tx_unicast": 5,
      "mac_acked": 5,
      "mac_rx": 13,
      "mac_rx_error": 0,
      "mac_rx_collision": 0,
      "mac_ack_error": 0,
      "mac_parent_tx_unicast": 5,
      "mac_parent_acked": 5,
      "mac_parent_rx": 12,
      "slots_rx_idle": 4037,
      "slots_rx_scanning": 29580,
      "slots_rx_packet": 0,
      "slots_rx_packet_tx_ack": 0,
      "slots_tx_packet": 14,
      "slots_tx_packet_rx_ack": 5,
      "tsch_join_time_sec": 295.8,
      "tsch_num_parent_changes": 1,
      "app_latency_min_s": null,
      "app_latency_avg_s": null,
      "app_latency_max_s": null,
      "app_latencies": [],
      "radio_duty_cycle": 50.813,
      "radio_duty_cycle_joined": 1.513,
      "charge_uc": 2158674.3,
      "charge_joined_uc": 88074.3,
      "avg_current_uA": 3597.8,
      "avg_current_joined_uA": 146.8,
      "routing_tx": 0,
      "routing_rx": 0,
      "routing_join_time_sec": 0,
      "routing_num_parent_changes": 1
    },
    "10": {
      "app_num_tx": 0,
      "app_num_replied": 0,
      "app_num_endpoint_rx": 0,
      "app_num_lost": 0,
      "app_reliability": 100,
      "app_num_queue_drops": 0,
      "app_num_tx_limit_drops": 0,
      "app_num_routing_drops": 0,
      "app_num_scheduling_drops": 0,
      "app_num_other_drops": 0,
      "tsch_eb_tx": 12,
      "tsch_eb_rx": 26,
      "tsch_keepalive_tx": 0,
      "tsch_keepalive_rx": 4,
      "mac_tx": 140,
      "mac_tx_unicast": 128,
      "mac_acked": 128,
      "mac_rx": 158,
      "mac_rx_error": 0,
      "mac_rx_collision": 4,
      "mac_ack_error": 0,
      "mac_parent_tx_unicast": 128,
      "mac_parent_acked": 128,
      "mac_parent_rx": 6,
      "slots_rx_idle": 6384,
      "slots_rx_scanning": 35040,
      "slots_rx_packet": 0,
      "slots_rx_packet_tx_ack": 132,
      "slots_tx_packet": 12,
      "slots_tx_packet_rx_ack": 128,
      "tsch_join_time_sec": 350.4,
      "tsch_num_parent_changes": 1,
      "app_latency_min_s": null,
      "app_latency_avg_s": null,
      "app_latency_max_s": null,
      "app_latencies": [],
      "radio_duty_cycle": 60.981,
      "radio_duty_cycle_joined": 2.581,
      "charge_uc": 2592078.3,
      "charge_joined_uc": 139278.3,
      "avg_current_uA": 4320.1,
      "avg_current_joined_uA": 232.1,
      "routing_tx": 0,
      "routing_rx": 0,
      "routing_join_time_sec": 0,
      "routing_num_parent_changes": 1
    },
    "11": {
      "app_num_tx": 0,
      "app_num_replied": 0,
      "app_num_endpoint_rx": 0,
      "app_num_lost": 0,
      "app_reliability": 100,
      "app_num_queue_drops": 0,
      "app_num_tx_limit_drops": 0,
      "app_num_routing_drops": 0,
      "app_num_scheduling_drops": 0,
      "app_num_other_drops": 0,
      "tsch_eb_tx": 30,
      "tsch_eb_rx": 30,
      "tsch_keepalive_tx": 8,
      "tsch_keepalive_rx": 0,
      "mac_tx": 38,
      "mac_tx_unicast": 8,
      "mac_acked": 8,
      "mac_rx": 30,
      "mac_rx_error": 0,
      "mac_rx_collision": 0,
      "mac_ack_error": 0,
      "mac_parent_tx_unicast": 8,
      "mac_parent_acked": 8,
      "mac_parent_rx": 29,
      "slots_rx_idle": 6650,
      "slots_rx_scanning": 9840,
      "slots_rx_packet": 0,
      "slots_rx_packet_tx_ack": 0,
      "slots_tx_packet": 30,
      "slots_tx_packet_rx_ack": 8,
      "tsch_join_time_sec": 98.4,
      "tsch_num_parent_changes": 1,
      "app_latency_min_s": null,
      "app_latency_avg_s": null,
      "app_latency_max_s": null,
      "app_latencies": [],
      "radio_duty_cycle": 18.876,
      "radio_duty_cycle_joined": 2.476,
      "charge_uc": 833881.6,
      "charge_joined_uc": 145081.6,
      "avg_current_uA": 1389.8,
      "avg_current_joined_uA": 241.8,
      "routing_tx": 0,
      "routing_rx": 0,
      "routing_join_time_sec": 0,
      "routing_num_parent_changes": 1
    },
    "12": {
      "app_num_tx": 0,
      "app_num_replied": 0,
      "app_num_endpoint_rx": 0,
      "app_num_lost": 0,
      "app_reliability": 100,
      "app_num_queue_drops": 0,
      "app_num_tx_limit_drops": 0,
      "app_num_routing_drops": 0,
      "app_num_scheduling_drops": 0,
      "app_num_other_drops": 0,
      "tsch_eb_tx": 14,
      "tsch_eb_rx": 11,
      "tsch_keepalive_tx": 4,
      "tsch_keepalive_rx": 0,
      "mac_tx": 18,
      "mac_tx_unicast": 4,
      "mac_acked": 4,
      "mac_rx": 13,
      "mac_rx_error": 0,
      "mac_rx_collision": 0,
      "mac_ack_error": 0,
      "mac_parent_tx_unicast": 4,
      "mac_parent_acked": 4,
      "mac_parent_rx": 10,
      "slots_rx_idle": 3024,
      "slots_rx_scanning": 37185,
      "slots_rx_packet": 0,
      "slots_rx_packet_tx_ack": 0,
      "slots_tx_packet": 14,
      "slots_tx_packet_rx_ack": 4,
      "tsch_join_time_sec": 371.85,
      "tsch_num_parent_changes": 1,
      "app_latency_min_s": null,
      "app_latency_avg_s": null,
      "app_latency_max_s": null,
      "app_latencies": [],
      "radio_duty_cycle": 63.116,
      "radio_duty_cycle_joined": 1.141,
      "charge_uc": 2668923.9,
      "charge_joined_uc": 65973.9,
      "avg_current_uA": 4448.2,
      "avg_current_joined_uA": 110,
      "routing_tx": 0,
      "routing_rx": 0,
      "routing_join_time_sec": 0,
      "routing_num_parent_changes": 1
    },
    "13": {
      "app_num_tx": 128,
      "app_num_replied": 0,
      "app_num_endpoint_rx": 0,
      "app_num_lost": 112,
      "app_reliability": 0,
      "app_num_queue_drops": 112,
      "app_num_tx_limit_drops": 0,
      "app_num_routing_drops": 0,
      "app_num_scheduling_drops": 0,
      "app_num_other_drops": 0,
      "tsch_eb_tx": 9,
      "tsch_eb_rx": 11,
      "tsch_keepalive_tx": 0,
      "tsch_keepalive_rx": 0,
      "mac_tx": 137,
      "mac_tx_unicast": 128,
      "mac_acked": 128,
      "mac_rx": 11,
      "mac_rx_error": 0,
      "mac_rx_collision": 0,
      "mac_ack_error": 0,
      "mac_parent_tx_unicast": 128,
      "mac_parent_acked": 128,
      "mac_parent_rx": 10,
      "slots_rx_idle": 3073,
      "slots_rx_scanning": 35925,
      "slots_rx_packet": 0,
      "slots_rx_packet_tx_ack": 0,
      "slots_tx_packet": 9,
      "slots_tx_packet_rx_ack": 128,
      "tsch_join_time_sec": 359.25,
      "tsch_num_parent_changes": 1,
      "app_latency_min_s": null,
      "app_latency_avg_s": null,
      "app_latency_max_s": null,
      "app_latencies": [],
      "radio_duty_cycle": 61.136,
      "radio_duty_cycle_joined": 1.261,
      "charge_uc": 2581792.9,
      "charge_joined_uc": 67042.9,
      "avg_current_uA": 4303,
      "avg_current_joined_uA": 111.7,
      "routing_tx": 0,
      "routing_rx": 0,
      "routing_join_time_sec": 0,
      "routing_num_parent_changes": 1
    },
    "global-stats": {
      "app-packets-sent": [
        {
          "total": 128,
          "name": "Number of application packets sent"
        }
      ],
      "app-packets-received": [
        {
          "total": 0,
          "name": "Number of application packets received"
        }
      ],
      "app-packets-lost": [
        {
          "total": 112,
          "name": "Number of application packets lost"
        }
      ],
      "app-packets-replied": [
        {
          "total": 0,
          "name": "Number of application query requests replied"
        }
      ],
      "current-consumed": [
        {
          "name": "Current consumed",
          "unit": "mA",
          "mean": 28.2
        }
      ],
      "current-consumed-when-joined": [
        {
          "name": "Current consumed",
          "unit": "mA",
          "mean": 4
        }
      ],
      "e2e-delivery": [
        {
          "value": 0,
          "name": "E2E delivery ratio",
          "unit": "%"
        },
        {
          "value": 100,
          "name": "E2E loss ratio",
          "unit": "%"
        }
      ],
      "e2e-latency": [
        {
          "name": "E2E latency",
          "min": null,
          "max": null,
          "unit": "s",
          "mean": null
        }
      ]
    }
  }
}