{
  "0": {
    "1": {
      "app_num_tx": 0,
      "app_num_replied": 0,
      "app_num_endpoint_rx": 0,
      "app_num_lost": 0,
      "app_reliability": 100,
      "app_num_queue_drops": 0,
      "app_num_tx_limit_drops": 0,
      "app_num_routing_drops": 0,
      "app_num_scheduling_drops": 0,
      "app_num_other_drops": 0,
      "tsch_eb_tx": 42,
      "tsch_eb_rx": 103,
      "tsch_keepalive_tx": 0,
      "tsch_keepalive_rx": 6,
      "mac_tx": 42,
      "mac_tx_unicast": 0,
      "mac_acked": 0,
      "mac_rx": 282,
      "mac_rx_error": 12,
      "mac_rx_collision": 0,
      "mac_ack_error": 0,
      "mac_parent_tx_unicast": 0,
      "mac_parent_acked": 0,
      "mac_parent_rx": 0,
      "slots_rx_idle": 47779,
      "slots_rx_scanning": 0,
      "slots_rx_packet": 0,
      "slots_rx_packet_tx_ack": 179,
      "slots_tx_packet": 42,
      "slots_tx_packet_rx_ack": 0,
      "tsch_join_time_sec": 0,
      "tsch_num_parent_changes": 0,
      "app_latency_min_s": null,
      "app_latency_avg_s": null,
      "app_latency_max_s": null,
      "app_latencies": [],
      "radio_duty_cycle": 17.699,
      "radio_duty_cycle_joined": 17.699,
      "charge_uc": 1042383.7,
      "charge_joined_uc": 1042383.7,
      "avg_current_uA": 1737.3,
      "avg_current_joined_uA": 1737.3,
      "routing_tx": 0,
      "routing_rx": 0,
      "routing_join_time_sec": 0,
      "routing_num_parent_changes": 1
    },
    "2": {
      "app_num_tx": 35,
      "app_num_replied": 0,
      "app_num_endpoint_rx": 35,
      "app_num_lost": 0,
      "app_reliability": 100,
      "app_num_queue_drops": 0,
      "app_num_tx_limit_drops": 0,
      "app_num_routing_drops": 0,
      "app_num_scheduling_drops": 0,
      "app_num_other_drops": 0,
      "tsch_eb_tx": 34,
      "tsch_eb_rx": 97,
      "tsch_keepalive_tx": 1,
      "tsch_keepalive_rx": 1,
      "mac_tx": 126,
      "mac_tx_unicast": 92,
      "mac_acked": 77,
      "mac_rx": 146,
      "mac_rx_error": 13,
      "mac_rx_collision": 2,
      "mac_ack_error": 10,
      "mac_parent_tx_unicast": 92,
      "mac_parent_acked": 77,
      "mac_parent_rx": 36,
      "slots_rx_idle": 32189,
      "slots_rx_scanning": 6060,
      "slots_rx_packet": 0,
      "slots_rx_packet_tx_ack": 49,
      "slots_tx_packet": 34,
      "slots_tx_packet_rx_ack": 92,
      "tsch_join_time_sec": 60.6,
      "tsch_num_parent_changes": 1,
      "app_latency_min_s": 0,
      "app_latency_avg_s": 0.027142857142857153,
      "app_latency_max_s": 0.13,
      "app_latencies": [
        0.04,
        0.02,
        0.02,
        0.01,
        0.01,
        0.13,
        0.01,
        0.04,
        0.01,
        0.01,
        0.04,
        0.04,
        0.03,
        0.03,
        0,
        0.02,
        0.11,
        0.03,
        0.04,
        0,
        0.03,
        0.04,
        0,
        0.02,
        0.04,
        0.02,
        0.01,
        0.01,
        0.04,
        0,
        0.04,
        0,
        0.03,
        0.01,
        0.02
      ],
      "radio_duty_cycle": 22.052,
      "radio_duty_cycle_joined": 11.952,
      "charge_uc": 1126460.2,
      "charge_joined_uc": 702260.2,
      "avg_current_uA": 1877.4,
      "avg_current_joined_uA": 1170.4,
      "routing_tx": 0,
      "routing_rx": 0,
      "routing_join_time_sec": 0,
      "routing_num_parent_changes": 1
    },
    "3": {
      "app_num_tx": 36,
      "app_num_replied": 0,
      "app_num_endpoint_rx": 36,
      "app_num_lost": 0,
      "app_reliability": 100,
      "app_num_queue_drops": 0,
      "app_num_tx_limit_drops": 0,
      "app_num_routing_drops": 0,
      "app_num_scheduling_drops": 0,
      "app_num_other_drops": 0,
      "tsch_eb_tx": 40,
      "tsch_eb_rx": 56,
      "tsch_keepalive_tx": 3,
      "tsch_keepalive_rx": 0,
      "mac_tx": 84,
      "mac_tx_unicast": 44,
      "mac_acked": 39,
      "mac_rx": 56,
      "mac_rx_error": 15,
      "mac_rx_collision": 0,
      "mac_ack_error": 2,
      "mac_parent_tx_unicast": 44,
      "mac_parent_acked": 39,
      "mac_parent_rx": 35,
      "slots_rx_idle": 23914,
      "slots_rx_scanning": 5,
      "slots_rx_packet": 0,
      "slots_rx_packet_tx_ack": 0,
      "slots_tx_packet": 40,
      "slots_tx_packet_rx_ack": 44,
      "tsch_join_time_sec": 0.05,
      "tsch_num_parent_changes": 1,
      "app_latency_min_s": 0,
      "app_latency_avg_s": 0.0263888888888889,
      "app_latency_max_s": 0.14,
      "app_latencies": [
        0.03,
        0.01,
        0.03,
        0,
        0.02,
        0,
        0,
        0.03,
        0.03,
        0.04,
        0.04,
        0.11,
        0.03,
        0,
        0.01,
        0.04,
        0,
        0.14,
        0.03,
        0.04,
        0.02,
        0.01,
        0.02,
        0.02,
        0.03,
        0.02,
        0.04,
        0.03,
        0,
        0.03,
        0,
        0.01,
        0.03,
        0.01,
        0.03,
        0.02
      ],
      "radio_duty_cycle": 8.847,
      "radio_duty_cycle_joined": 8.839,
      "charge_uc": 522076.3,
      "charge_joined_uc": 521726.3,
      "avg_current_uA": 870.1,
      "avg_current_joined_uA": 869.5,
      "routing_tx": 0,
      "routing_rx": 0,
      "routing_join_time_sec": 0,
      "routing_num_parent_changes": 1
    },
    "4": {
      "app_num_tx": 38,
      "app_num_replied": 0,
      "app_num_endpoint_rx": 38,
      "app_num_lost": 0,
      "app_reliability": 100,
      "app_num_queue_drops": 0,
      "app_num_tx_limit_drops": 0,
      "app_num_routing_drops": 0,
      "app_num_scheduling_drops": 0,
      "app_num_other_drops": 0,
      "tsch_eb_tx": 42,
      "tsch_eb_rx": 36,
      "tsch_keepalive_tx": 2,
      "tsch_keepalive_rx": 0,
      "mac_tx": 99,
      "mac_tx_unicast": 57,
      "mac_acked": 40,
      "mac_rx": 36,
      "mac_rx_error": 9,
      "mac_rx_collision": 0,
      "mac_ack_error": 11,
      "mac_parent_tx_unicast": 57,
      "mac_parent_acked": 40,
      "mac_parent_rx": 35,
      "slots_rx_idle": 23899,
      "slots_rx_scanning": 5,
      "slots_rx_packet": 0,
      "slots_rx_packet_tx_ack": 0,
      "slots_tx_packet": 42,
      "slots_tx_packet_rx_ack": 57,
      "tsch_join_time_sec": 0.05,
      "tsch_num_parent_changes": 1,
      "app_latency_min_s": 0,
      "app_latency_avg_s": 0.025263157894736852,
      "app_latency_max_s": 0.18,
      "app_latencies": [
        0.01,
        0.02,
        0,
        0,
        0.04,
        0.04,
        0.02,
        0.04,
        0,
        0.03,
        0.02,
        0.01,
        0.01,
        0,
        0.03,
        0,
        0.02,
        0.02,
        0.02,
        0.04,
        0,
        0.02,
        0.03,
        0.02,
        0.03,
        0.02,
        0.04,
        0.04,
        0.02,
        0.02,
        0.01,
        0.03,
        0.02,
        0.02,
        0.03,
        0.18,
        0.02,
        0.04
      ],
      "radio_duty_cycle": 8.853,
      "radio_duty_cycle_joined": 8.845,
      "charge_uc": 521749.1,
      "charge_joined_uc": 521399.1,
      "avg_current_uA": 869.6,
      "avg_current_joined_uA": 869,
      "routing_tx": 0,
      "routing_rx": 0,
      "routing_join_time_sec": 0,
      "routing_num_parent_changes": 1
    },
    "5": {
      "app_num_tx": 41,
      "app_num_replied": 0,
      "app_num_endpoint_rx": 41,
      "app_num_lost": 0,
      "app_reliability": 100,
      "app_num_queue_drops": 0,
      "app_num_tx_limit_drops": 0,
      "app_num_routing_drops": 0,
      "app_num_scheduling_drops": 0,
      "app_num_other_drops": 0,
      "tsch_eb_tx": 38,
      "tsch_eb_rx": 29,
      "tsch_keepalive_tx": 1,
      "tsch_keepalive_rx": 0,
      "mac_tx": 91,
      "mac_tx_unicast": 53,
      "mac_acked": 42,
      "mac_rx": 29,
      "mac_rx_error": 7,
      "mac_rx_collision": 0,
      "mac_ack_error": 7,
      "mac_parent_tx_unicast": 53,
      "mac_parent_acked": 42,
      "mac_parent_rx": 28,
      "slots_rx_idle": 21169,
      "slots_rx_scanning": 6850,
      "slots_rx_packet": 0,
      "slots_rx_packet_tx_ack": 0,
      "slots_tx_packet": 38,
      "slots_tx_packet_rx_ack": 53,
      "tsch_join_time_sec": 68.5,
      "tsch_num_parent_changes": 1,
      "app_latency_min_s": 0.01,
      "app_latency_avg_s": 0.041951219512195145,
      "app_latency_max_s": 0.16,
      "app_latencies": [
        0.05,
        0.02,
        0.04,
        0.01,
        0.03,
        0.01,
        0.02,
        0.01,
        0.05,
        0.13,
        0.08,
        0.03,
        0.04,
        0.01,
        0.05,
        0.03,
        0.03,
        0.05,
        0.08,
        0.04,
        0.05,
        0.04,
        0.02,
        0.08,
        0.09,
        0.04,
        0.16,
        0.04,
        0.05,
        0.02,
        0.02,
        0.02,
        0.04,
        0.02,
        0.02,
        0.02,
        0.03,
        0.02,
        0.04,
        0.04,
        0.05
      ],
      "radio_duty_cycle": 19.257,
      "radio_duty_cycle_joined": 7.841,
      "charge_uc": 941339.3,
      "charge_joined_uc": 461839.3,
      "avg_current_uA": 1568.9,
      "avg_current_joined_uA": 769.7,
      "routing_tx": 0,
      "routing_rx": 0,
      "routing_join_time_sec": 0,
      "routing_num_parent_changes": 1
    },
    "6": {
      "app_num_tx": 41,
      "app_num_replied": 0,
      "app_num_endpoint_rx": 0,
      "app_num_lost": 39,
      "app_reliability": 0,
      "app_num_queue_drops": 0,
      "app_num_tx_limit_drops": 39,
      "app_num_routing_drops": 0,
      "app_num_scheduling_drops": 0,
      "app_num_other_drops": 0,
      "tsch_eb_tx": 30,
      "tsch_eb_rx": 51,
      "tsch_keepalive_tx": 6,
      "tsch_keepalive_rx": 0,
      "mac_tx": 1050,
      "mac_tx_unicast": 1020,
      "mac_acked": 0,
      "mac_rx": 196,
      "mac_rx_error": 96,
      "mac_rx_collision": 0,
      "mac_ack_error": 0,
      "mac_parent_tx_unicast": 1020,
      "mac_parent_acked": 0,
      "mac_parent_rx": 46,
      "slots_rx_idle": 25338,
      "slots_rx_scanning": 15855,
      "slots_rx_packet": 0,
      "slots_rx_packet_tx_ack": 99,
      "slots_tx_packet": 30,
      "slots_tx_packet_rx_ack": 1020,
      "tsch_join_time_sec": 68.5,
      "tsch_num_parent_changes": 7,
      "app_latency_min_s": null,
      "app_latency_avg_s": null,
      "app_latency_max_s": null,
      "app_latencies": [],
      "radio_duty_cycle": 36.642,
      "radio_duty_cycle_joined": 10.217,
      "charge_uc": 1662643.4,
      "charge_joined_uc": 552793.4,
      "avg_current_uA": 2771.1,
      "avg_current_joined_uA": 921.3,
      "routing_tx": 0,
      "routing_rx": 0,
      "routing_join_time_sec": 0,
      "routing_num_parent_changes": 1
    },
    "7": {
      "app_num_tx": 27,
      "app_num_replied": 0,
      "app_num_endpoint_rx": 0,
      "app_num_lost": 27,
      "app_reliability": 0,
      "app_num_queue_drops": 0,
      "app_num_tx_limit_drops": 27,
      "app_num_routing_drops": 0,
      "app_num_scheduling_drops": 0,
      "app_num_other_drops": 0,
      "tsch_eb_tx": 23,
      "tsch_eb_rx": 24,
      "tsch_keepalive_tx": 5,
      "tsch_keepalive_rx": 0,
      "mac_tx": 279,
      "mac_tx_unicast": 256,
      "mac_acked": 0,
      "mac_rx": 31,
      "mac_rx_error": 8,
      "mac_rx_collision": 0,
      "mac_ack_error": 0,
      "mac_parent_tx_unicast": 256,
      "mac_parent_acked": 0,
      "mac_parent_rx": 18,
      "slots_rx_idle": 12819,
      "slots_rx_scanning": 27255,
      "slots_rx_packet": 0,
      "slots_rx_packet_tx_ack": 0,
      "slots_tx_packet": 23,
      "slots_tx_packet_rx_ack": 256,
      "tsch_join_time_sec": 141.9,
      "tsch_num_parent_changes": 5,
      "app_latency_min_s": null,
      "app_latency_avg_s": null,
      "app_latency_max_s": null,
      "app_latencies": [],
      "radio_duty_cycle": 50.35,
      "radio_duty_cycle_joined": 4.925,
      "charge_uc": 2187519.2,
      "charge_joined_uc": 279669.2,
      "avg_current_uA": 3645.9,
      "avg_current_joined_uA": 466.1,
      "routing_tx": 0,
      "routing_rx": 0,
      "routing_join_time_sec": 0,
      "routing_num_parent_changes": 1
    },
    "8": {
      "app_num_tx": 41,
      "app_num_replied": 0,
      "app_num_endpoint_rx": 0,
      "app_num_lost": 39,
      "app_reliability": 0,
      "app_num_queue_drops": 0,
      "app_num_tx_limit_drops": 39,
      "app_num_routing_drops": 0,
      "app_num_scheduling_drops": 0,
      "app_num_other_drops": 0,
      "tsch_eb_tx": 33,
      "tsch_eb_rx": 81,
      "tsch_keepalive_tx": 0,
      "tsch_keepalive_rx": 0,
      "mac_tx": 343,
      "mac_tx_unicast": 310,
      "mac_acked": 84,
      "mac_rx": 1071,
      "mac_rx_error": 29,
      "mac_rx_collision": 2,
      "mac_ack_error": 15,
      "mac_parent_tx_unicast": 310,
      "mac_parent_acked": 84,
      "mac_parent_rx": 938,
      "slots_rx_idle": 37915,
      "slots_rx_scanning": 10945,
      "slots_rx_packet": 912,
      "slots_rx_packet_tx_ack": 74,
      "slots_tx_packet": 33,
      "slots_tx_packet_rx_ack": 310,
      "tsch_join_time_sec": 109.45,
      "tsch_num_parent_changes": 1,
      "app_latency_min_s": null,
      "app_latency_avg_s": null,
      "app_latency_max_s": null,
      "app_latencies": [],
      "radio_duty_cycle": 33.098,
      "radio_duty_cycle_joined": 14.857,
      "charge_uc": 1593333,
      "charge_joined_uc": 827183,
      "avg_current_uA": 2655.6,
      "avg_current_joined_uA": 1378.6,
      "routing_tx": 0,
      "routing_rx": 0,
      "routing_join_time_sec": 0,
      "routing_num_parent_changes": 1
    },
    "9": {
      "app_num_tx": 34,
      "app_num_replied": 0,
      "app_num_endpoint_rx": 0,
      "app_num_lost": 34,
      "app_reliability": 0,
      "app_num_queue_drops": 0,
      "app_num_tx_limit_drops": 34,
      "app_num_routing_drops": 0,
      "app_num_scheduling_drops": 0,
      "app_num_other_drops": 0,
      "tsch_eb_tx": 31,
      "tsch_eb_rx": 22,
      "tsch_keepalive_tx": 0,
      "tsch_keepalive_rx": 0,
      "mac_tx": 72,
      "mac_tx_unicast": 41,
      "mac_acked": 34,
      "mac_rx": 24,
      "mac_rx_error": 9,
      "mac_rx_collision": 0,
      "mac_ack_error": 2,
      "mac_parent_tx_unicast": 41,
      "mac_parent_acked": 34,
      "mac_parent_rx": 21,
      "slots_rx_idle": 17380,
      "slots_rx_scanning": 16370,
      "slots_rx_packet": 0,
      "slots_rx_packet_tx_ack": 0,
      "slots_tx_packet": 31,
      "slots_tx_packet_rx_ack": 41,
      "tsch_join_time_sec": 163.7,
      "tsch_num_parent_changes": 1,
      "app_latency_min_s": null,
      "app_latency_avg_s": null,
      "app_latency_max_s": null,
      "app_latencies": [],
      "radio_duty_cycle": 33.724,
      "radio_duty_cycle_joined": 6.441,
      "charge_uc": 1525075.5,
      "charge_joined_uc": 379175.5,
      "avg_current_uA": 2541.8,
      "avg_current_joined_uA": 632,
      "routing_tx": 0,
      "routing_rx": 0,
      "routing_join_time_sec": 0,
      "routing_num_parent_changes": 1
    },
    "10": {
      "app_num_tx": 34,
      "app_num_replied": 0,
      "app_num_endpoint_rx": 0,
      "app_num_lost": 34,
      "app_reliability": 0,
      "app_num_queue_drops": 0,
      "app_num_tx_limit_drops": 34,
      "app_num_routing_drops": 0,
      "app_num_scheduling_drops": 0,
      "app_num_other_drops": 0,
      "tsch_eb_tx": 29,
      "tsch_eb_rx": 52,
      "tsch_keepalive_tx": 0,
      "tsch_keepalive_rx": 0,
      "mac_tx": 72,
      "mac_tx_unicast": 43,
      "mac_acked": 34,
      "mac_rx": 57,
      "mac_rx_error": 8,
      "mac_rx_collision": 0,
      "mac_ack_error": 4,
      "mac_parent_tx_unicast": 43,
      "mac_parent_acked": 34,
      "mac_parent_rx": 23,
      "slots_rx_idle": 16756,
      "slots_rx_scanning": 17930,
      "slots_rx_packet": 0,
      "slots_rx_packet_tx_ack": 0,
      "slots_tx_packet": 29,
      "slots_tx_packet_rx_ack": 43,
      "tsch_join_time_sec": 179.3,
      "tsch_num_parent_changes": 1,
      "app_latency_min_s": null,
      "app_latency_avg_s": null,
      "app_latency_max_s": null,
      "app_latencies": [],
      "radio_duty_cycle": 36.096,
      "radio_duty_cycle_joined": 6.213,
      "charge_uc": 1620661.9,
      "charge_joined_uc": 365561.9,
      "avg_current_uA": 2701.1,
      "avg_current_joined_uA": 609.3,
      "routing_tx": 0,
      "routing_rx": 0,
      "routing_join_time_sec": 0,
      "routing_num_parent_changes": 1
    },
    "11": {
      "app_num_tx": 2,
      "app_num_replied": 0,
      "app_num_endpoint_rx": 0,
      "app_num_lost": 2,
      "app_reliability": 0,
      "app_num_queue_drops": 0,
      "app_num_tx_limit_drops": 2,
      "app_num_routing_drops": 0,
      "app_num_scheduling_drops": 0,
      "app_num_other_drops": 0,
      "tsch_eb_tx": 3,
      "tsch_eb_rx": 4,
      "tsch_keepalive_tx": 1,
      "tsch_keepalive_rx": 0,
      "mac_tx": 27,
      "mac_tx_unicast": 24,
      "mac_acked": 0,
      "mac_rx": 59,
      "mac_rx_error": 0,
      "mac_rx_collision": 0,
      "mac_ack_error": 0,
      "mac_parent_tx_unicast": 24,
      "mac_parent_acked": 0,
      "mac_parent_rx": 3,
      "slots_rx_idle": 1847,
      "slots_rx_scanning": 55315,
      "slots_rx_packet": 0,
      "slots_rx_packet_tx_ack": 0,
      "slots_tx_packet": 3,
      "slots_tx_packet_rx_ack": 24,
      "tsch_join_time_sec": 553.15,
      "tsch_num_parent_changes": 1,
      "app_latency_min_s": null,
      "app_latency_avg_s": null,
      "app_latency_max_s": null,
      "app_latencies": [],
      "radio_duty_cycle": 92.913,
      "radio_duty_cycle_joined": 0.721,
      "charge_uc": 3912345.6,
      "charge_joined_uc": 40295.6,
      "avg_current_uA": 6520.6,
      "avg_current_joined_uA": 67.2,
      "routing_tx": 0,
      "routing_rx": 0,
      "routing_join_time_sec": 0,
      "routing_num_parent_changes": 1
    },
    "12": {
      "app_num_tx": 21,
      "app_num_replied": 0,
      "app_num_endpoint_rx": 0,
      "app_num_lost": 0,
      "app_reliability": 100,
      "app_num_queue_drops": 0,
      "app_num_tx_limit_drops": 0,
      "app_num_routing_drops": 0,
      "app_num_scheduling_drops": 0,
      "app_num_other_drops": 0,
      "tsch_eb_tx": 17,
      "tsch_eb_rx": 17,
      "tsch_keepalive_tx": 4,
      "tsch_keepalive_rx": 0,
      "mac_tx": 17,
      "mac_tx_unicast": 0,
      "mac_acked": 0,
      "mac_rx": 25,
      "mac_rx_error": 5,
      "mac_rx_collision": 0,
      "mac_ack_error": 0,
      "mac_parent_tx_unicast": 0,
      "mac_parent_acked": 0,
      "mac_parent_rx": 14,
      "slots_rx_idle": 9645,
      "slots_rx_scanning": 35845,
      "slots_rx_packet": 0,
      "slots_rx_packet_tx_ack": 0,
      "slots_tx_packet": 17,
      "slots_tx_packet_rx_ack": 0,
      "tsch_join_time_sec": 180.7,
      "tsch_num_parent_changes": 5,
      "app_latency_min_s": null,
      "app_latency_avg_s": null,
      "app_latency_max_s": null,
      "app_latencies": [],
      "radio_duty_cycle": 63.309,
      "radio_duty_cycle_joined": 3.568,
      "charge_uc": 2719572.8,
      "charge_joined_uc": 210422.8,
      "avg_current_uA": 4532.6,
      "avg_current_joined_uA": 350.7,
      "routing_tx": 0,
      "routing_rx": 0,
      "routing_join_time_sec": 0,
      "routing_num_parent_changes": 1
    },
    "13": {
      "app_num_tx": 24,
      "app_num_replied": 0,
      "app_num_endpoint_rx": 0,
      "app_num_lost": 0,
      "app_reliability": 100,
      "app_num_queue_drops": 0,
      "app_num_tx_limit_drops": 0,
      "app_num_routing_drops": 0,
      "app_num_scheduling_drops": 0,
      "app_num_other_drops": 0,
      "tsch_eb_tx": 16,
      "tsch_eb_rx": 16,
      "tsch_keepalive_tx": 4,
      "tsch_keepalive_rx": 0,
      "mac_tx": 16,
      "mac_tx_unicast": 0,
      "mac_acked": 0,
      "mac_rx": 24,
      "mac_rx_error": 0,
      "mac_rx_collision": 0,
      "mac_ack_error": 0,
      "mac_parent_tx_unicast": 0,
      "mac_parent_acked": 0,
      "mac_parent_rx": 13,
      "slots_rx_idle": 4815,
      "slots_rx_scanning": 35845,
      "slots_rx_packet": 0,
      "slots_rx_packet_tx_ack": 0,
      "slots_tx_packet": 16,
      "slots_tx_packet_rx_ack": 0,
      "tsch_join_time_sec": 270.75,
      "tsch_num_parent_changes": 5,
      "app_latency_min_s": null,
      "app_latency_avg_s": null,
      "app_latency_max_s": null,
      "app_latencies": [],
      "radio_duty_cycle": 61.538,
      "radio_duty_cycle_joined": 1.796,
      "charge_uc": 2614197.8,
      "charge_joined_uc": 105047.8,
      "avg_current_uA": 4357,
      "avg_current_joined_uA": 175.1,
      "routing_tx": 0,
      "routing_rx": 0,
      "routing_join_time_sec": 0,
      "routing_num_parent_changes": 1
    },
    "global-stats": {
      "app-packets-sent": [
        {
          "total": 374,
          "name": "Number of application packets sent"
        }
      ],
      "app-packets-received": [
        {
          "total": 150,
          "name": "Number of application packets received"
        }
      ],
      "app-packets-lost": [
        {
          "total": 175,
          "name": "Number of application packets lost"
        }
      ],
      "app-packets-replied": [
        {
          "total": 0,
          "name": "Number of application query requests replied"
        }
      ],
      "current-consumed": [
        {
          "name": "Current consumed",
          "unit": "mA",
          "mean": 36.6
        }
      ],
      "current-consumed-when-joined": [
        {
          "name": "Current consumed",
          "unit": "mA",
          "mean": 10
        }
      ],
      "e2e-delivery": [
        {
          "value": 46.15384615384615,
          "name": "E2E delivery ratio",
          "unit": "%"
        },
        {
          "value": 53.84615384615385,
          "name": "E2E loss ratio",
          "unit": "%"
        }
      ],
      "e2e-latency": [
        {
          "name": "E2E latency",
          "min": 0,
          "max": 0.18,
          "unit": "s",
          "mean": 0.030533333333333298
        }
      ]
    }
  }
}